Workbook

Sheet Resumen
A1: Costos del primer año (USD)
A2: No incluye horas de desarrollo ni de mantención. Precios revisados en octubre de 2026.
A4: Escenario | B4: Pagos únicos | C4: Anuales obligatorios | D4: Servicios 12 meses | E4: Total año 1 | F4: Desde el año 2 (por año)
A5: Validación (5 conductores) | B5: ='Pagos únicos'!B6 -> 424 | C5: ='Pagos anuales'!B7 -> 111 | D5: =12*Mensual!C13 -> 516 | E5: =B5+C5+D5 -> 1051 | F5: =C5+D5 -> 627
A6: 100 conductores (mínimo) | B6: ='Pagos únicos'!B6 -> 424 | C6: ='Pagos anuales'!B7 -> 111 | D6: =12*Mensual!D13 -> 2700 | E6: =B6+C6+D6 -> 3235 | F6: =C6+D6 -> 2811
A7: 100 conductores (máximo) | B7: ='Pagos únicos'!B6 -> 424 | C7: ='Pagos anuales'!B7 -> 111 | D7: =12*Mensual!E13 -> 4656 | E7: =B7+C7+D7 -> 5191 | F7: =C7+D7 -> 4767
A9: Por conductor al mes (100 conductores, máximo) | E9: =Mensual!E13/Supuestos!B4 -> 3.88
A11: Si se eligiera Opus 5.5 para la IA, sumar unos USD 200 a 400 al mes con 100 conductores (decisión: Sonnet 5.5 + Haiku 5.5).

Sheet Pagos únicos
A1: Pagos únicos (USD)
A3: Qué | B3: Costo USD | C3: Cuánto dura | D3: Cuándo se paga | E3: Fuente
A4: Licencia plugin de GPS (Transistorsoft Starter) | B4: 399 | C4: Para siempre (la clave no vence). Cubre Android e iOS. | D4: Al publicar en las tiendas | E4: docs.transistorsoft.com/purchase
A5: Cuenta Google Play | B5: 25 | C5: Para siempre | D5: Al publicar en Android | E5: Precio público Google Play (oct-2026)
A6: Total pagos únicos | B6: =SUM(B4:B5) -> 424

Sheet Pagos anuales
A1: Pagos anuales (USD por año)
A3: Qué | B3: Costo USD/año | C3: ¿Obligatorio? | D3: Duración | E3: Si no se renueva | F3: Fuente
A4: Cuenta Apple Developer | B4: 99 | C4: Sí | D4: 1 año | E4: La app se retira del App Store | F4: Precio público Apple (oct-2026)
A5: Dominio .cl (NIC Chile) | B5: 12 | C5: Sí | D5: 1 año | E5: Se pierde la dirección web | F5: Aproximado, confirmar en nic.cl
A6: Soporte y actualizaciones del plugin de GPS | B6: 199 | C6: No | D6: 1 año | E6: La app sigue funcionando, sin versiones nuevas | F6: docs.transistorsoft.com/help/faq
A7: Total anual obligatorio | B7: =SUMIFS(B4:B6,C4:C6,"Sí") -> 111
A8: Total anual con soporte del plugin | B8: =SUM(B4:B6) -> 310

Sheet Mensual
A1: Pagos mensuales (USD por mes)
A3: Servicio | B3: Para qué | C3: Validación (5 conductores) | D3: 100 conductores (mínimo) | E3: 100 conductores (máximo) | F3: Contrato | G3: Fuente
A4: Supabase Pro | B4: Base de datos, cuentas, tiempo real, fotos | C4: 25 | D4: 90 | E4: 110 | F4: Mes a mes | G4: supabase.com/pricing
A5: VPS (servidor propio) | B5: Rutas, hora estimada y direcciones | C5: 15 | D5: 30 | E5: 30 | F5: Mes a mes | G5: Proveedor VPS, a definir en Etapa D
A6: Claude Sonnet 5.5 + Haiku 5.5 | B6: Asistente de IA | C6: 3 | D6: 80 | E6: 120 | F6: Por uso | G6: Precios Anthropic: Sonnet $2/$10, Haiku $0,10/$0,50 por millón de tokens
A7: Resend | B7: Correos con códigos de acceso | C7: 0 | D7: 20 | E7: 20 | F7: Mes a mes | G7: resend.com/pricing
A8: Stream | B8: Llamadas dentro de la app | C8: 0 | D8: 0 | E8: 18 | F8: Por uso | G8: getstream.io/video/pricing ($0,30 / 1.000 min-participante)
A9: Google Geocoding | B9: Direcciones difíciles (respaldo) | C9: 0 | D9: 0 | E9: 20 | F9: Por uso | G9: Google Maps Platform
A10: Cloudflare | B10: Web del panel y archivo de mapas | C10: 0 | D10: 5 | E10: 25 | F10: Mes a mes | G10: cloudflare.com
A11: Sentry | B11: Aviso de errores | C11: 0 | D11: 0 | E11: 26 | F11: Mes a mes | G11: sentry.io/pricing
A12: Expo EAS | B12: Compilar la app | C12: 0 | D12: 0 | E12: 19 | F12: Mes a mes | G12: expo.dev/pricing
A13: Total mensual | C13: =SUM(C4:C12) -> 43 | D13: =SUM(D4:D12) -> 225 | E13: =SUM(E4:E12) -> 388
A15: Azul = valor ingresado a mano (puedes cambiarlo). Negro = fórmula. Todos los servicios son sin contrato y se pueden cancelar.

Sheet Supuestos
A1: Supuestos de volumen (100 conductores)
A3: Dato | B3: Valor | C3: Nota
A4: Conductores | B4: 100 | C4: Escenario de escala
A5: Entregas por conductor al día | B5: 20 | C5: Supuesto
A6: Días hábiles al mes | B6: 24 | C6: Supuesto
A7: Entregas al mes | B7: =B4*B5*B6 -> 48000 | C7: Fórmula
A8: Envío de ubicación (segundos) | B8: 15 | C8: Cada 15 s o 50 m
A9: Fotos por entrega | B9: 3 | C9: ~250 KB cada una
A10: Entregas con llamada | B10: 0.3 | C10: 2 minutos promedio
A11: Retención del recorrido GPS (días) | B11: 30 | C11: Política de privacidad

Sheet Decisiones
A1: Decisiones tomadas
A3: Tema | B3: Decisión
A4: Plataformas | B4: Android e iOS (una sola app con React Native/Expo) + panel web del administrador + web con código para el receptor
A5: Ubicación en segundo plano | B5: Plugin Transistorsoft, licencia Starter USD 399 pago único
A6: Asistente de IA | B6: Claude Sonnet 5.5 (órdenes) + Haiku 5.5 (clasificar y redactar). Modos 'propone' o 'responde solo', a elección del administrador
A7: Llamadas | B7: Dentro de la app (VoIP) con Stream, sin mostrar números
A8: Inicio de sesión | B8: Código por correo electrónico (sin SMS, sin contraseña)
A9: Datos del conductor | B9: Nombre, foto de licencia, documentos del camión (opcional), correo, teléfono
A10: Datos del administrador | B10: Empresa, nombre, teléfono, foto (opcional); varios administradores por empresa
A11: Datos del receptor | B11: Nombre, teléfono y correo si instala la app; o código web sin cuenta
A12: Código del receptor | B12: Lo genera el asistente; el administrador lo envía por privado
A13: Cobros | B13: Fuera de la app; el receptor informa con foto de transferencia o efectivo
A14: Carga de entregas | B14: Una por una o por archivo Excel/CSV con vista previa
... A21: Pendiente | B21: Nombre de la app y datos de la empresa para los textos legales

Sheet Fases
A1: Fases de construcción
A3: Fase | B3: Qué incluye | C3: Listo cuando…
A4: 0. Cimientos | B4: Repositorio, base de datos de desarrollo, pruebas automáticas, colores y tipografías | C4: La app abre en tu teléfono y la web en tu computador
A5: 1. Cuentas y perfiles | B5: Registro de los 3 perfiles, código por correo, varios administradores, invitar conductores, términos | C5: Cada perfil entra con su código y solo ve lo suyo
A6: 2. Entregas y asignación | B6: Crear entrega, carga por Excel con vista previa, direcciones en el mapa, sectores | C6: Subes un Excel de 50 filas y ves listas, por revisar y con error
A7: 3. Conductor: el día | B7: Ruta del día, iniciar/terminar, llegué, foto, cobro, Waze/Maps | C7: Con dos teléfonos haces el día de Matías y el administrador ve cada cambio
A8: 4. Ubicación en tiempo real | B8: Plugin de GPS, consentimiento, mapa en vivo | C8: 1 hora de ruta real con Waze abierto sin cortes en el mapa
A9: 5. Receptor | B9: Web con código, app con cuenta, seguimiento, pago, comprobante, notificaciones | C9: Sofía ve solo su paquete; el de Pedro aparece solo en su app
A10: 6. Mensajería | B10: Chats, tablero, mensajes programados | C10: El aviso de las 08:20 sale a esa hora
A11: 7. Asistente de IA | B11: Herramientas, dos modos, auditoría, límites | C11: 'Avísale a Sofía…' funciona y queda registrado
A12: 8. Hora estimada y retraso | B12: Rutas propias, cerca/llegó, alerta de retraso, orden de entregas | C12: El simulador del día de Matías pasa completo
A13: 9. Llamadas | B13: App a app y web, timbre con app cerrada, sin números | C13: Suena como llamada normal con la app cerrada
A14: 10. Sin señal | B14: Cola de fotos y eventos, reintentos, sin duplicados | C14: En modo avión entregas y al volver la señal se sube una vez
A15: 11. Legal y cierre | B15: Descargar/borrar datos, retención automática, respaldos | C15: Borras tu cuenta de prueba y desaparece
